[
  { "title": "Wilkommen bei Sapling", "person": 1, "entity": "note" },
  { "title": "Aktive Unternehmen", "person": 1, "entity": "company", "filter": "{\"isActive\":true}" },
  { "title": "Unternehmen mit Website", "person": 1, "entity": "company", "filter": "{\"website\":{$ne:null}}" },
  { "title": "Unternehmen in Berlin", "person": 1, "entity": "company", "filter": "{\"city\":\"Berlin\"}" },
  { "title": "Personen: Aktiv", "person": 2, "entity": "person", "filter": "{\"isActive\":true}" },
  { "title": "Personen mit Mobilnummer", "person": 2, "entity": "person", "filter": "{\"mobile\":{$ne:null}}" },
  { "title": "Personen mit Geburtstag im November", "person": 2, "entity": "person", "filter": "{\"birthDay\":{$gte:\"2025-11-01\",$lte:\"2025-11-30\"}}" },
  { "title": "Tickets: Offen", "person": 2, "entity": "ticket", "filter": "{\"status\":\"open\"}" },
  { "title": "Tickets mit hoher Priorität", "person": 2, "entity": "ticket", "filter": "{\"priority\":1}" },
  { "title": "Tickets mit Deadline heute", "person": 2, "entity": "ticket", "filter": "{\"deadlineDate\":\"2025-11-02\"}" },
  { "title": "Produkte: Beta-Versionen", "person": 2, "entity": "product", "filter": "{\"version\":{$lt:\"1.0.0\"}}" },
  { "title": "Produkte mit Beschreibung", "person": 2, "entity": "product", "filter": "{\"description\":{$ne:null}}" },
  { "title": "Verträge: Aktiv", "person": 1, "entity": "contract", "filter": "{\"isActive\":true}" },
  { "title": "Verträge mit Enddatum 2025", "person": 1, "entity": "contract", "filter": "{\"endDate\":{$gte:\"2025-01-01\",$lte:\"2025-12-31\"}}" },
  { "title": "Verträge mit Antwortzeit < 12h", "person": 1, "entity": "contract", "filter": "{\"responseTimeHours\":{$lt:12}}" },
  { "title": "Sprachen: Deutsch", "person": 2, "entity": "translation", "filter": "{\"language\":\"de\"}" },
  { "title": "Übersetzungen für Ticket", "person": 2, "entity": "translation", "filter": "{\"entity\":\"Ticket\"}" },
  { "title": "Übersetzungen für Property description", "person": 2, "entity": "translation", "filter": "{\"property\":\"description\"}" },
  { "title": "Entitäten mit Lese-Recht", "person": 1, "entity": "entity", "filter": "{\"canRead\":true}" },
  { "title": "Entitäten mit Icon star", "person": 1, "entity": "entity", "filter": "{\"icon\":\"star\"}" },
  { "title": "Entitäten mit Route gesetzt", "person": 1, "entity": "entity", "filter": "{\"route\":{$ne:null}}" },
  { "title": "Unternehmen mit Telefonnummer", "person": 2, "entity": "company", "filter": "{\"phone\":{$ne:null}}" },
  { "title": "Personen mit Sprache Deutsch", "person": 2, "entity": "person", "filter": "{\"language\":\"Deutsch\"}" }
]